flask_unsign_wordlist/__init__.py
flask_unsign_wordlist/exceptions.py
flask_unsign_wordlist/wordlists/all.txt
flask_unsign_wordlist/wordlists/github.txt
flask_unsign_wordlist/wordlists/gitlab.txt
flask_unsign_wordlist/wordlists/searchcode.txt
flask_unsign_wordlist/wordlists/stackexchange.txt
flask_unsign_wordlist/wordlists/stackoverflow.txt
flask_unsign_wordlist-2024.1.dist-info/LICENSE.md
flask_unsign_wordlist-2024.1.dist-info/METADATA
flask_unsign_wordlist-2024.1.dist-info/WHEEL
flask_unsign_wordlist-2024.1.dist-info/entry_points.txt
flask_unsign_wordlist-2024.1.dist-info/top_level.txt
flask_unsign_wordlist-2024.1.dist-info/RECORD
