Metadata-Version: 2.1
Name: flask-unsign-wordlist
Version: 2024.1
Summary: The following package is the standalone wordlist-only component to flask-unsign. For more information, see: https://github.com/Paradoxis/Flask-Unsign
Home-page: https://github.com/Paradoxis/Flask-Unsign-Wordlist
Author: Luke Paris (Paradoxis)
Author-email: luke@paradoxis.nl
License: MIT
Classifier: License :: OSI Approved :: MIT License
Classifier: Programming Language :: Python
Classifier: Programming Language :: Python :: 3
Classifier: Programming Language :: Python :: 3.6
Classifier: Programming Language :: Python :: Implementation :: CPython
Classifier: Programming Language :: Python :: Implementation :: PyPy
Requires-Python: >=3.6.0
License-File: LICENSE.md
Provides-Extra: dev
Requires-Dist: twine ; extra == 'dev'
Requires-Dist: wheel ; extra == 'dev'
Requires-Dist: setuptools >=40.6.3 ; extra == 'dev'
Provides-Extra: test
Requires-Dist: coverage ; extra == 'test'
Requires-Dist: codecov ; extra == 'test'
